[
  {
    "ain": "8448-008-048",
    "address": "1609 CALLE CRISTINA, SAN DIMAS CA 91773-4470",
    "useType": "Single Family Residence",
    "parcelStatus": "ACTIVE",
    "taxStatus": "CURRENT",
    "yearBuilt": "1991",
    "beds": 4,
    "baths": 5,
    "bldg": 4356,
    "lot": 157314,
    "assessed": 1479172,
    "ownerKnown": "Paul M. & Mary M. Smith, Trustees (Smith Family Trust)",
    "lastBuy": { "rec": "03/06/2019", "doc": "0198701", "price": "1300013" },
    "market": "OFF_MARKET",
    "hasForeclosureHist": true,
    "fcNote": "Historical foreclosure doc 03/12/1997 only"
  },
  {
    "ain": "8448-008-055",
    "address": "1603 CALLE CRISTINA, SAN DIMAS CA 91773-4470",
    "useType": "Single Family Residence",
    "parcelStatus": "ACTIVE",
    "taxStatus": "CURRENT",
    "yearBuilt": "1991",
    "beds": 5,
    "baths": 6,
    "bldg": 6838,
    "lot": 126660,
    "assessed": 1807678,
    "ownerKnown": "D. Daniela H. Angelo (individual); trust transfer 2016",
    "lastBuy": { "rec": "11/20/2001", "doc": "2209767", "price": "1025000" },
    "market": "LISTED_OR_RECENT_OFF_MARKET_~3300000_MLS_CV26035893",
    "hasForeclosureHist": false
  }
]
