[
  {
    "ain": "8455-025-001",
    "parcel": {
      "AIN": "8455025001",
      "Latitude": 34.0735215997,
      "Longitude": -117.914223061,
      "SitusStreet": "1502 E SHAMWOOD ST",
      "SitusCity": "WEST COVINA CA",
      "SitusZipCode": "91791-1318",
      "UseType": "Single Family Residence",
      "ParcelStatus": "ACTIVE",
      "TaxStatus": "CURRENT",
      "YearBuilt": "1951",
      "SqftLot": 7510,
      "SqftMain": 1550,
      "NumOfBeds": 4,
      "NumOfBaths": 2,
      "CurrentRoll_LandValue": 141022,
      "CurrentRoll_ImpValue": 130469
    }
  },
  {
    "ain": "8455-025-002",
    "parcel": {
      "AIN": "8455025002",
      "Latitude": 34.0735231189,
      "Longitude": -117.914410868,
      "SitusStreet": "1442 E SHAMWOOD ST",
      "SitusCity": "WEST COVINA CA",
      "SitusZipCode": "91791-1316",
      "UseType": "Single Family Residence",
      "ParcelStatus": "ACTIVE",
      "TaxStatus": "CURRENT",
      "YearBuilt": "1951",
      "SqftLot": 7503,
      "SqftMain": 1118,
      "NumOfBeds": 3,
      "NumOfBaths": 2,
      "CurrentRoll_LandValue": 435829,
      "CurrentRoll_ImpValue": 194432
    }
  },
  {
    "ain": "8455-025-003",
    "parcel": {
      "AIN": "8455025003",
      "Latitude": 34.0735244501,
      "Longitude": -117.91459799,
      "SitusStreet": "1438 E SHAMWOOD ST",
      "SitusCity": "WEST COVINA CA",
      "SitusZipCode": "91791-1316",
      "UseType": "Single Family Residence",
      "ParcelStatus": "ACTIVE",
      "TaxStatus": "CURRENT",
      "YearBuilt": "1951",
      "SqftLot": 7455,
      "SqftMain": 1130,
      "NumOfBeds": 3,
      "NumOfBaths": 2,
      "CurrentRoll_LandValue": 362245,
      "CurrentRoll_ImpValue": 167328
    }
  },
  {
    "ain": "8455-025-004",
    "parcel": {
      "AIN": "8455025004",
      "Latitude": 34.0735254805,
      "Longitude": -117.914785085,
      "SitusStreet": "1434 E SHAMWOOD ST",
      "SitusCity": "WEST COVINA CA",
      "SitusZipCode": "91791-1316",
      "UseType": "Single Family Residence",
      "ParcelStatus": "ACTIVE",
      "TaxStatus": "CURRENT",
      "YearBuilt": "1951",
      "SqftLot": 7501,
      "SqftMain": 1358,
      "NumOfBeds": 3,
      "NumOfBaths": 2,
      "CurrentRoll_LandValue": 311339,
      "CurrentRoll_ImpValue": 195053
    }
  },
  {
    "ain": "8455-025-005",
    "parcel": {
      "AIN": "8455025005",
      "Latitude": 34.07353412,
      "Longitude": -117.914981365,
      "SitusStreet": "1430 E SHAMWOOD ST",
      "SitusCity": "WEST COVINA CA",
      "SitusZipCode": "91791-1316",
      "UseType": "Single Family Residence",
      "ParcelStatus": "ACTIVE",
      "TaxStatus": "CURRENT",
      "YearBuilt": "1951",
      "SqftLot": 7993,
      "SqftMain": 1686,
      "NumOfBeds": 3,
      "NumOfBaths": 2,
      "CurrentRoll_LandValue": 128326,
      "CurrentRoll_ImpValue": 182522
    }
  },
  {
    "ain": "8455-025-006",
    "parcel": {
      "AIN": "8455025006",
      "Latitude": 34.073548766,
      "Longitude": -117.91519873,
      "SitusStreet": "1426 E SHAMWOOD ST",
      "SitusCity": "WEST COVINA CA",
      "SitusZipCode": "91791-1316",
      "UseType": "Single Family Residence",
      "ParcelStatus": "ACTIVE",
      "TaxStatus": "CURRENT",
      "YearBuilt": "1951",
      "SqftLot": 8105,
      "SqftMain": 1328,
      "NumOfBeds": 3,
      "NumOfBaths": 2,
      "CurrentRoll_LandValue": 163968,
      "CurrentRoll_ImpValue": 121323
    }
  },
  {
    "ain": "8455-025-007",
    "parcel": {
      "AIN": "8455025007",
      "Latitude": 34.0735652668,
      "Longitude": -117.915436175,
      "SitusStreet": "1420 E SHAMWOOD ST",
      "SitusCity": "WEST COVINA CA",
      "SitusZipCode": "91791-1316",
      "UseType": "Single Family Residence",
      "ParcelStatus": "ACTIVE",
      "TaxStatus": "CURRENT",
      "YearBuilt": "1951",
      "SqftLot": 8015,
      "SqftMain": 1118,
      "NumOfBeds": 3,
      "NumOfBaths": 2,
      "CurrentRoll_LandValue": 197918,
      "CurrentRoll_ImpValue": 151256
    }
  },
  {
    "ain": "8455-025-008",
    "parcel": {
      "AIN": "8455025008",
      "Latitude": 34.0735829786,
      "Longitude": -117.915691858,
      "SitusStreet": "1414 E SHAMWOOD ST",
      "SitusCity": "WEST COVINA CA",
      "SitusZipCode": "91791-1316",
      "UseType": "Single Family Residence",
      "ParcelStatus": "ACTIVE",
      "TaxStatus": "CURRENT",
      "YearBuilt": "1951",
      "SqftLot": 7637,
      "SqftMain": 1530,
      "NumOfBeds": 3,
      "NumOfBaths": 2,
      "CurrentRoll_LandValue": 145981,
      "CurrentRoll_ImpValue": 119435
    }
  },
  {
    "ain": "8455-025-013",
    "parcel": {
      "AIN": "8455025013",
      "Latitude": 34.0733160669,
      "Longitude": -117.915724366,
      "SitusStreet": "1415 E MARDINA ST",
      "SitusCity": "WEST COVINA CA",
      "SitusZipCode": "91791-1309",
      "UseType": "Single Family Residence",
      "ParcelStatus": "ACTIVE",
      "TaxStatus": "CURRENT",
      "YearBuilt": "1951",
      "SqftLot": 7698,
      "SqftMain": 2043,
      "NumOfBeds": 3,
      "NumOfBaths": 2,
      "CurrentRoll_LandValue": 223593,
      "CurrentRoll_ImpValue": 199589
    }
  },
  {
    "ain": "8455-025-014",
    "parcel": {
      "AIN": "8455025014",
      "Latitude": 34.0732747419,
      "Longitude": -117.9154801,
      "SitusStreet": "1419 E MARDINA ST",
      "SitusCity": "WEST COVINA CA",
      "SitusZipCode": "91791-1309",
      "UseType": "Single Family Residence",
      "ParcelStatus": "ACTIVE",
      "TaxStatus": "CURRENT",
      "YearBuilt": "1951",
      "SqftLot": 8153,
      "SqftMain": 1694,
      "NumOfBeds": 4,
      "NumOfBaths": 3,
      "CurrentRoll_LandValue": 57985,
      "CurrentRoll_ImpValue": 205456
    }
  },
  {
    "ain": "8455-025-015",
    "parcel": {
      "AIN": "8455025015",
      "Latitude": 34.0732363904,
      "Longitude": -117.915244973,
      "SitusStreet": "1425 E MARDINA ST",
      "SitusCity": "WEST COVINA CA",
      "SitusZipCode": "91791-1309",
      "UseType": "Single Family Residence",
      "ParcelStatus": "ACTIVE",
      "TaxStatus": "CURRENT",
      "YearBuilt": "1951",
      "SqftLot": 7908,
      "SqftMain": 1130,
      "NumOfBeds": 3,
      "NumOfBaths": 2,
      "CurrentRoll_LandValue": 83018,
      "CurrentRoll_ImpValue": 135555
    }
  },
  {
    "ain": "8455-025-016",
    "parcel": {
      "AIN": "8455025016",
      "Latitude": 34.0731969691,
      "Longitude": -117.915025294,
      "SitusStreet": "1427 E MARDINA ST",
      "SitusCity": "WEST COVINA CA",
      "SitusZipCode": "91791-1309",
      "UseType": "Single Family Residence",
      "ParcelStatus": "ACTIVE",
      "TaxStatus": "CURRENT",
      "YearBuilt": "1951",
      "SqftLot": 7906,
      "SqftMain": 1675,
      "NumOfBeds": 3,
      "NumOfBaths": 2,
      "CurrentRoll_LandValue": 637557,
      "CurrentRoll_ImpValue": 173954
    }
  },
  {
    "ain": "8455-025-017",
    "parcel": {
      "AIN": "8455025017",
      "Latitude": 34.0731660669,
      "Longitude": -117.914809722,
      "SitusStreet": "1433 E MARDINA ST",
      "SitusCity": "WEST COVINA CA",
      "SitusZipCode": "91791-1309",
      "UseType": "Single Family Residence",
      "ParcelStatus": "ACTIVE",
      "TaxStatus": "CURRENT",
      "YearBuilt": "1951",
      "SqftLot": 8256,
      "SqftMain": 1118,
      "NumOfBeds": 3,
      "NumOfBaths": 2,
      "CurrentRoll_LandValue": 124807,
      "CurrentRoll_ImpValue": 123072
    }
  },
  {
    "ain": "8455-025-018",
    "parcel": {
      "AIN": "8455025018",
      "Latitude": 34.0731583754,
      "Longitude": -117.914601744,
      "SitusStreet": "1439 E MARDINA ST",
      "SitusCity": "WEST COVINA CA",
      "SitusZipCode": "91791-1309",
      "UseType": "Single Family Residence",
      "ParcelStatus": "ACTIVE",
      "TaxStatus": "CURRENT",
      "YearBuilt": "1951",
      "SqftLot": 8022,
      "SqftMain": 1130,
      "NumOfBeds": 3,
      "NumOfBaths": 2,
      "CurrentRoll_LandValue": 144986,
      "CurrentRoll_ImpValue": 144986
    }
  },
  {
    "ain": "8455-025-019",
    "parcel": {
      "AIN": "8455025019",
      "Latitude": 34.073160407,
      "Longitude": -117.914407448,
      "SitusStreet": "1443 E MARDINA ST",
      "SitusCity": "WEST COVINA CA",
      "SitusZipCode": "91791-1309",
      "UseType": "Single Family Residence",
      "ParcelStatus": "ACTIVE",
      "TaxStatus": "CURRENT",
      "YearBuilt": "1951",
      "SqftLot": 7494,
      "SqftMain": 1511,
      "NumOfBeds": 4,
      "NumOfBaths": 3,
      "CurrentRoll_LandValue": 268854,
      "CurrentRoll_ImpValue": 104735
    }
  },
  {
    "ain": "8455-025-020",
    "parcel": {
      "AIN": "8455025020",
      "Latitude": 34.0731589189,
      "Longitude": -117.914219815,
      "SitusStreet": "1503 E MARDINA ST",
      "SitusCity": "WEST COVINA CA",
      "SitusZipCode": "91791-1311",
      "UseType": "Single Family Residence",
      "ParcelStatus": "ACTIVE",
      "TaxStatus": "CURRENT",
      "YearBuilt": "1951",
      "SqftLot": 7504,
      "SqftMain": 1130,
      "NumOfBeds": 3,
      "NumOfBaths": 2,
      "CurrentRoll_LandValue": 614820,
      "CurrentRoll_ImpValue": 153703
    }
  },
  {
    "ain": "8455-025-023",
    "parcel": {
      "AIN": "8455025023",
      "Latitude": 34.0735936168,
      "Longitude": -117.916000664,
      "SitusStreet": "1408 E SHAMWOOD ST",
      "SitusCity": "WEST COVINA CA",
      "SitusZipCode": "91791-1316",
      "UseType": "Single Family Residence",
      "ParcelStatus": "ACTIVE",
      "TaxStatus": "CURRENT",
      "YearBuilt": "1951",
      "SqftLot": 9361,
      "SqftMain": 1118,
      "NumOfBeds": 3,
      "NumOfBaths": 2,
      "CurrentRoll_LandValue": 468916,
      "CurrentRoll_ImpValue": 105835
    }
  },
  {
    "ain": "8455-025-024",
    "parcel": {
      "AIN": "8455025024",
      "Latitude": 34.0733482032,
      "Longitude": -117.916007872,
      "SitusStreet": "1407 E MARDINA ST",
      "SitusCity": "WEST COVINA CA",
      "SitusZipCode": "91791-1309",
      "UseType": "Single Family Residence",
      "ParcelStatus": "ACTIVE",
      "TaxStatus": "CURRENT",
      "YearBuilt": "1951",
      "SqftLot": 9260,
      "SqftMain": 1130,
      "NumOfBeds": 3,
      "NumOfBaths": 2,
      "CurrentRoll_LandValue": 468515,
      "CurrentRoll_ImpValue": 123149
    }
  }
]